MANIFEST.in
README.md
setup.py
siterank/__init__.py
siterank/siterank.py
siterank.egg-info/PKG-INFO
siterank.egg-info/SOURCES.txt
siterank.egg-info/dependency_links.txt
siterank.egg-info/entry_points.txt
siterank.egg-info/requires.txt
siterank.egg-info/top_level.txt