Metadata-Version: 2.1
Name: siterank
Version: 1.0.2
Summary: get alexa global rank for a given website or domain
Home-page: https://github.com/prahladyeri/siterank
Author: Prahlad Yeri
Author-email: prahladyeri@yahoo.com
License: MIT
Keywords: internet
Platform: UNKNOWN
Classifier: Programming Language :: Python :: 3
Classifier: License :: OSI Approved :: MIT License
Classifier: Operating System :: OS Independent
